[
  {
    "title": "Welcome to the M1 Windows project",
    "url": "https://amarioguy.github.io/m1windowsproject/",
    "upvotes": 329,
    "author": "giuliomagnifico",
    "comments": 158,
    "link": "https://news.ycombinator.com/item?id=31657591"
  },
  {
    "title": "Embodiment Is Indispensable for AGI",
    "url": "https://keerthanapg.com/tech/embodiment-agi/",
    "upvotes": 39,
    "author": "keerthanpg",
    "comments": 24,
    "link": "https://news.ycombinator.com/item?id=31660272"
  },
  {
    "title": "Dhall: A Gateway Drug to Haskell",
    "url": "https://www.saurabhnanda.in/2022/03/24/dhall-a-gateway-drug-to-haskell/",
    "upvotes": 99,
    "author": "todsacerdoti",
    "comments": 67,
    "link": "https://news.ycombinator.com/item?id=31658638"
  },
  {
    "title": "When Shipping Containers Sink in the Drink",
    "url": "https://www.newyorker.com/magazine/2022/06/06/when-shipping-containers-sink-in-the-drink",
    "upvotes": 18,
    "author": "frenchman_in_ny",
    "comments": 2,
    "link": "https://news.ycombinator.com/item?id=31660571"
  },
  {
    "title": "Behind the Ferrari and Lamborghini rivalry",
    "url": "https://www.granturismoevents.com/story-the-epic-story-behind-the-ferrari-and-lamborghini-rivalry/",
    "upvotes": 46,
    "author": "mhb",
    "comments": 17,
    "link": "https://news.ycombinator.com/item?id=31639268"
  },
  {
    "title": "What ID3v2 could have been",
    "url": "https://underjord.io/id3-specification-and-speculation.html",
    "upvotes": 72,
    "author": "lawik",
    "comments": 36,
    "link": "https://news.ycombinator.com/item?id=31658664"
  },
  {
    "title": "Show HN: The Bitcoin Note – Secure, Self-Custodial Bitcoin Wallets in Cash Form",
    "url": "https://www.offline.cash/",
    "upvotes": 225,
    "author": "paulgerhardt",
    "comments": 343,
    "link": "https://news.ycombinator.com/item?id=31653726"
  },
  {
    "title": "Liquid platinum at room temperature: possible revolution in industrial chemistry",
    "url": "https://phys.org/news/2022-06-liquid-platinum-room-temperature-cool.html",
    "upvotes": 162,
    "author": "PaulHoule",
    "comments": 52,
    "link": "https://news.ycombinator.com/item?id=31653887"
  },
  {
    "title": "EU reaches deal to make USB-C a common charger for most electronic devices",
    "url": "https://www.engadget.com/eu-reaches-deal-to-make-usb-c-a-common-charger-for-most-electronic-devices-104605067.html",
    "upvotes": 388,
    "author": "geox",
    "comments": 773,
    "link": "https://news.ycombinator.com/item?id=31652291"
  },
  {
    "title": "Tesorio",
    "url": "https://jobs.lever.co/tesorio/dcc1de3f-e6ac-4c02-97d0-78138c8138a5"
  },
  {
    "title": "Show HN: Umbrel – A personal server OS for self-hosting",
    "url": "https://umbrel.com",
    "upvotes": 88,
    "author": "mayankchhabra",
    "comments": 53,
    "link": "https://news.ycombinator.com/item?id=31657527"
  },
  {
    "title": "What’s the best lossless image format?",
    "url": "https://siipo.la/blog/whats-the-best-lossless-image-format-comparing-png-webp-avif-and-jpeg-xl",
    "upvotes": 113,
    "author": "pmoriarty",
    "comments": 73,
    "link": "https://news.ycombinator.com/item?id=31657006"
  },
  {
    "title": "Many researchers were not compliant with their published data sharing statement",
    "url": "https://www.jclinepi.com/article/S0895-4356(22)00141-X/pdf",
    "upvotes": 13,
    "author": "miohtama",
    "comments": 6,
    "link": "https://news.ycombinator.com/item?id=31660239"
  },
  {
    "title": "FAA Continues to Stall on G100UL",
    "url": "https://www.avweb.com/insider/faa-continues-to-stall-on-g100ul/",
    "upvotes": 70,
    "author": "sklargh",
    "comments": 33,
    "link": "https://news.ycombinator.com/item?id=31657607"
  },
  {
    "title": "Show HN: SetOps – Run containers, databases and more in your own AWS account",
    "url": "https://www.setops.co/",
    "upvotes": 31,
    "author": "latebird22",
    "comments": 14,
    "link": "https://news.ycombinator.com/item?id=31654696"
  },
  {
    "title": "How to Draw Animals",
    "url": "http://dessinoprimaire.blogspot.com/2012/02/les-animaux-tels-quils-sont.html",
    "upvotes": 133,
    "author": "ddtaylor",
    "comments": 57,
    "link": "https://news.ycombinator.com/item?id=31628181"
  },
  {
    "title": "EndBASIC",
    "url": "https://www.endbasic.dev/",
    "upvotes": 48,
    "author": "tosh",
    "comments": 39,
    "link": "https://news.ycombinator.com/item?id=31651881"
  },
  {
    "title": "Germany paying $5.5B for Intel fab",
    "url": "https://www.electronicsweekly.com/news/business/793299-2022-03/",
    "upvotes": 388,
    "author": "throwaway4good",
    "comments": 444,
    "link": "https://news.ycombinator.com/item?id=31654762"
  },
  {
    "title": "Joy: A maximalist web framework for Lisp aficionados",
    "url": "https://joy.swlkr.com/",
    "upvotes": 167,
    "author": "memorable",
    "comments": 58,
    "link": "https://news.ycombinator.com/item?id=31654257"
  },
  {
    "title": "How does a logic gate in a microchip work?",
    "url": "https://www.scientificamerican.com/article/how-does-a-logic-gate-in/",
    "upvotes": 10,
    "author": "ofou",
    "comments": null,
    "link": "https://news.ycombinator.com/item?id=31650782"
  },
  {
    "title": "Please, don't build another Large Hadron Collider",
    "url": "https://bigthink.com/hard-science/large-hadron-collider-economics/",
    "upvotes": 315,
    "author": "khaled_ismaeel",
    "comments": 422,
    "link": "https://news.ycombinator.com/item?id=31651086"
  },
  {
    "title": "We're moving to a four-day work week at Beacon",
    "url": "https://www.beaconcrm.org/blog/beacon-switching-to-four-day-work-week",
    "upvotes": 342,
    "author": "500and4",
    "comments": 305,
    "link": "https://news.ycombinator.com/item?id=31651423"
  },
  {
    "title": "Inbound container volumes to the US are reverting to pre-pandemic levels",
    "url": "https://www.freightwaves.com/news/us-import-demand-drops-off-a-cliff",
    "upvotes": 207,
    "author": "strict9",
    "comments": 218,
    "link": "https://news.ycombinator.com/item?id=31657068"
  },
  {
    "title": "Launch HN: Rootly (YC S21) – Manage Incidents in Slack",
    "url": "item?id=31653985",
    "upvotes": 92,
    "author": "kwent",
    "comments": 62,
    "link": "https://news.ycombinator.com/item?id=31653985"
  },
  {
    "title": "Cloture – Implementation of Clojure in Common Lisp",
    "url": "https://github.com/ruricolist/cloture",
    "upvotes": 85,
    "author": "capableweb",
    "comments": 7,
    "link": "https://news.ycombinator.com/item?id=31655574"
  },
  {
    "title": "In Algeria, Ancient Cave Art May Show Psychedelic Mushroom Use",
    "url": "https://www.atlasobscura.com/articles/psychedelic-mushroom-algeria",
    "upvotes": 48,
    "author": "prismatic",
    "comments": 33,
    "link": "https://news.ycombinator.com/item?id=31648995"
  },
  {
    "title": "Please don't unofficially ship Bottles in distribution repositories",
    "url": "https://usebottles.com/blog/an-open-letter/",
    "upvotes": 47,
    "author": "ddtaylor",
    "comments": 50,
    "link": "https://news.ycombinator.com/item?id=31658086"
  },
  {
    "title": "Eliminating Toil",
    "url": "https://sre.google/sre-book/eliminating-toil/",
    "upvotes": 270,
    "author": "omarfarooq",
    "comments": 78,
    "link": "https://news.ycombinator.com/item?id=31651146"
  },
  {
    "title": "The firefly population could be declining",
    "url": "https://www.wesa.fm/environment-energy/2022-06-07/the-firefly-population-could-be-declining-heres-why",
    "upvotes": 210,
    "author": "dontbenebby",
    "comments": 207,
    "link": "https://news.ycombinator.com/item?id=31652781"
  },
  {
    "title": "I've locked myself out of my digital life",
    "url": "https://shkspr.mobi/blog/2022/06/ive-locked-myself-out-of-my-digital-life/",
    "upvotes": 617,
    "author": "edent",
    "comments": 426,
    "link": "https://news.ycombinator.com/item?id=31652650"
  }
]
