[
  {
    "title": "Abandoned Motorola Headquarters",
    "url": "https://www.abandonedspaces.com/industry/motorola.html",
    "upvotes": 225,
    "author": "sonograph",
    "comments": 101,
    "link": "https://news.ycombinator.com/item?id=28171123"
  },
  {
    "title": "Egui: An easy-to-use immediate mode GUI",
    "url": "https://github.com/emilk/egui",
    "upvotes": 255,
    "author": "ducktective",
    "comments": 105,
    "link": "https://news.ycombinator.com/item?id=28166663"
  },
  {
    "title": "FOSS app removed from the Play Store for linking to the project's website",
    "url": "https://github.com/language-transfer/lt-app/pull/44",
    "upvotes": 443,
    "author": "timothyaveni",
    "comments": 148,
    "link": "https://news.ycombinator.com/item?id=28172490"
  },
  {
    "title": "Apple Regrets Confusion over 'iPhone Scanning'",
    "url": "https://www.bbc.com/news/technology-58206543",
    "upvotes": 169,
    "author": "belter",
    "comments": 260,
    "link": "https://news.ycombinator.com/item?id=28172269"
  },
  {
    "title": "WinCompose – A Compose Key for Windows",
    "url": "https://github.com/samhocevar/wincompose",
    "upvotes": 151,
    "author": "mkotowski",
    "comments": 74,
    "link": "https://news.ycombinator.com/item?id=28169705"
  },
  {
    "title": "EasyPost is building the logistics platform for ecommerce",
    "url": "https://www.easypost.com/careers"
  },
  {
    "title": "Interactive Linear Algebra",
    "url": "http://textbooks.math.gatech.edu/ila/index.html",
    "upvotes": 227,
    "author": "natemcintosh",
    "comments": 33,
    "link": "https://news.ycombinator.com/item?id=28168339"
  },
  {
    "title": "Dad makes teddies with health conditions to help children with medical disorders",
    "url": "https://inews.co.uk/news/real-life/this-leeds-dad-makes-teddies-with-health-conditions-to-help-children-living-with-medical-disorders-1148392",
    "upvotes": 347,
    "author": "zeristor",
    "comments": 71,
    "link": "https://news.ycombinator.com/item?id=28166741"
  },
  {
    "title": "Show HN: Instantly Listen to Any URL",
    "url": "https://per.quest/",
    "upvotes": 80,
    "author": "soheil",
    "comments": 29,
    "link": "https://news.ycombinator.com/item?id=28170609"
  },
  {
    "title": "Archaeologists discover 4k-year-old ancient city in Iraqi desert",
    "url": "https://www.theartnewspaper.com/news/archaeologists-discover-4-000-year-old-ancient-city-in-iraqi-desert",
    "upvotes": 29,
    "author": "andyxor",
    "comments": 12,
    "link": "https://news.ycombinator.com/item?id=28171965"
  },
  {
    "title": "How Google bought Android",
    "url": "https://arstechnica.com/information-technology/2021/08/excerpt-the-history-of-android-as-written-by-a-longtime-android-developer/",
    "upvotes": 177,
    "author": "samizdis",
    "comments": 93,
    "link": "https://news.ycombinator.com/item?id=28167690"
  },
  {
    "title": "Descartes’s Evil Genius",
    "url": "https://lareviewofbooks.org/article/descartess-evil-genius/",
    "upvotes": 27,
    "author": "drdee",
    "comments": null,
    "link": "https://news.ycombinator.com/item?id=28148729"
  },
  {
    "title": "Co-founder of Snopes was writing plagiarized articles under a fake name",
    "url": "https://www.buzzfeednews.com/article/deansterlingjones/snopes-cofounder-plagiarism-mikkelson",
    "upvotes": 308,
    "author": "danso",
    "comments": 286,
    "link": "https://news.ycombinator.com/item?id=28169681"
  },
  {
    "title": "On the Nature of Merge Conflicts",
    "url": "https://neverworkintheory.org/2021/08/12/on-the-nature-of-merge-conflicts.html",
    "upvotes": 5,
    "author": "zdw",
    "comments": null,
    "link": "https://news.ycombinator.com/item?id=28159477"
  },
  {
    "title": "Launch HN: Iona Mind (YC S21) – App-based cognitive behavioural therapy",
    "url": "item?id=28168336",
    "upvotes": 66,
    "author": "phowson83",
    "comments": 43,
    "link": "https://news.ycombinator.com/item?id=28168336"
  },
  {
    "title": "First step in making programming easier is to be concious of what makes it hard",
    "url": "http://lighttable.com/2014/05/16/pain-we-forgot/",
    "upvotes": 26,
    "author": "b3morales",
    "comments": 21,
    "link": "https://news.ycombinator.com/item?id=28171894"
  },
  {
    "title": "Adda as a Way of Life",
    "url": "https://www.bbc.com/travel/article/20210812-adda-the-secret-to-bengali-conviviality",
    "upvotes": 74,
    "author": "ramirez60",
    "comments": 30,
    "link": "https://news.ycombinator.com/item?id=28168933"
  },
  {
    "title": "Paint by Numbers: How Roger de Piles tabulated artistic merit",
    "url": "https://www.laphamsquarterly.org/roundtable/paint-numbers",
    "upvotes": 9,
    "author": "prismatic",
    "comments": null,
    "link": "https://news.ycombinator.com/item?id=28161618"
  },
  {
    "title": "What if Planet 9 is a Primordial Black Hole?",
    "url": "https://arxiv.org/abs/1909.11090",
    "upvotes": 133,
    "author": "rbanffy",
    "comments": 121,
    "link": "https://news.ycombinator.com/item?id=28167058"
  },
  {
    "title": "Launch HN: FirstIgnite (YC S21) – Matching scientists with relevant businesses",
    "url": "item?id=28168813",
    "upvotes": 54,
    "author": "codypilot",
    "comments": 25,
    "link": "https://news.ycombinator.com/item?id=28168813"
  },
  {
    "title": "WHO inquiry chief 'had concerns' about lab close to first Covid cases",
    "url": "https://apnews.com/article/entertainment-joe-biden-business-health-coronavirus-pandemic-986f0ff0f97af020de3b4eb3d76b23cd",
    "upvotes": 155,
    "author": "belter",
    "comments": 122,
    "link": "https://news.ycombinator.com/item?id=28171452"
  },
  {
    "title": "Apple's child protection features spark concern within its own ranks: sources",
    "url": "https://www.reuters.com/technology/exclusive-apples-child-protection-features-spark-concern-within-its-own-ranks-2021-08-12/",
    "upvotes": 1565,
    "author": "spenvo",
    "comments": 736,
    "link": "https://news.ycombinator.com/item?id=28162412"
  },
  {
    "title": "Do not do in code what can be done in infrastructure",
    "url": "https://rogerjohansson.blog/2017/05/19/do-not-do-in-code-what-can-be-done-in-infrastructure/",
    "upvotes": 101,
    "author": "alfiedotwtf",
    "comments": 81,
    "link": "https://news.ycombinator.com/item?id=28167416"
  },
  {
    "title": "Scientists retrace steps of Ice Age mammoth over its entire lifetime",
    "url": "https://www.cbc.ca/news/science/mammoth-tusk-1.6139008",
    "upvotes": 43,
    "author": "worldvoyageur",
    "comments": 13,
    "link": "https://news.ycombinator.com/item?id=28168418"
  },
  {
    "title": "New Anti Anti-Money Laundering Services for Crooks",
    "url": "https://krebsonsecurity.com/2021/08/new-anti-anti-money-laundering-services-for-crooks/",
    "upvotes": 15,
    "author": "parsecs",
    "comments": 2,
    "link": "https://news.ycombinator.com/item?id=28171867"
  },
  {
    "title": "Mozilla tests if 'Firefox/100.0' user agent breaks websites",
    "url": "https://www.bleepingcomputer.com/news/software/mozilla-tests-if-firefox-1000-user-agent-breaks-websites/",
    "upvotes": 20,
    "author": "Pick-A-Hill2019",
    "comments": 6,
    "link": "https://news.ycombinator.com/item?id=28173909"
  },
  {
    "title": "The Psychology of Human Misjudgment",
    "url": "https://fsmisc.s3.ca-central-1.amazonaws.com/great-talks/The+Psychology+of+Human+Misjudment.pdf",
    "upvotes": 19,
    "author": "openquery",
    "comments": 3,
    "link": "https://news.ycombinator.com/item?id=28168311"
  },
  {
    "title": "The Secretive, Semi-Illicit World of WhatsApp Mango Importing",
    "url": "https://www.eater.com/22618349/pakistani-mangoes-chaunsa-anwar-ratol-buy-usa-whatsapp-shipping-supply-chain",
    "upvotes": 115,
    "author": "ryzvonusef",
    "comments": 83,
    "link": "https://news.ycombinator.com/item?id=28166646"
  },
  {
    "title": "Show HN: Judo - Build Native App Experiences with No Code",
    "url": "https://www.judo.app/",
    "upvotes": 93,
    "author": "krzyzanowskim",
    "comments": 61,
    "link": "https://news.ycombinator.com/item?id=28167368"
  },
  {
    "title": "Jackson structured programming",
    "url": "https://en.wikipedia.org/wiki/Jackson_structured_programming",
    "upvotes": 91,
    "author": "haakonhr",
    "comments": 61,
    "link": "https://news.ycombinator.com/item?id=28154890"
  }
]
