[
  {
    "title": "Amazon Pip Horror Story",
    "url": "https://archive.fo/pdYHy",
    "upvotes": 204,
    "author": "vikinghckr",
    "comments": 144,
    "link": "https://news.ycombinator.com/item?id=30203581"
  },
  {
    "title": "Go performance from version 1.2 to 1.18",
    "url": "https://benhoyt.com/writings/go-version-performance/",
    "upvotes": 238,
    "author": "todsacerdoti",
    "comments": 129,
    "link": "https://news.ycombinator.com/item?id=30201969"
  },
  {
    "title": "Non-Consensual Personalization",
    "url": "https://amitp.blogspot.com/2022/02/non-consensual-personalization.html",
    "upvotes": 190,
    "author": "zdw",
    "comments": 115,
    "link": "https://news.ycombinator.com/item?id=30178781"
  },
  {
    "title": "How the World Went from Post-Politics to Hyper-Politics",
    "url": "https://tribunemag.co.uk/2022/01/from-post-politics-to-hyper-politics",
    "upvotes": 34,
    "author": "bryanrasmussen",
    "comments": 13,
    "link": "https://news.ycombinator.com/item?id=30203429"
  },
  {
    "title": "Where in the World Are Trader Joe’s Warehouses?",
    "url": "https://sburer.github.io/2015/06/02/Trader-Joes.html",
    "upvotes": 61,
    "author": "walkersutton",
    "comments": 23,
    "link": "https://news.ycombinator.com/item?id=30203019"
  },
  {
    "title": "Mysterious aircraft spotted at Area 51 in satellite image",
    "url": "https://www.thedrive.com/the-war-zone/44057/mysterious-aircraft-spotted-at-area-51-in-unprecedented-satellite-image",
    "upvotes": 196,
    "author": "benlumen",
    "comments": 108,
    "link": "https://news.ycombinator.com/item?id=30193450"
  },
  {
    "title": "Why Are Mathematicians So Bad at Arithmetic?",
    "url": "https://mathwithbaddrawings.com/2017/01/11/why-are-mathematicians-so-bad-at-arithmetic/",
    "upvotes": 28,
    "author": "tomerv",
    "comments": 14,
    "link": "https://news.ycombinator.com/item?id=30190338"
  },
  {
    "title": "The Karikó problem: Lessons for funding basic research",
    "url": "https://www.statnews.com/2022/02/01/kariko-problem-lessons-funding-basic-research/",
    "upvotes": 251,
    "author": "hatmatrix",
    "comments": 134,
    "link": "https://news.ycombinator.com/item?id=30198239"
  },
  {
    "title": "Ask HN: How can I make a “kid's computer” today as good as an Apple II?",
    "url": "item?id=30186091",
    "upvotes": 38,
    "author": "qq66",
    "comments": 35,
    "link": "https://news.ycombinator.com/item?id=30186091"
  },
  {
    "title": "Dip Switch USB Stick",
    "url": "https://twitter.com/bikerglen/status/1482516332432162820",
    "upvotes": 186,
    "author": "tambourine_man",
    "comments": 61,
    "link": "https://news.ycombinator.com/item?id=30198730"
  },
  {
    "title": "Applying Event-Driven Architecture in Digital Transformation Projects",
    "url": "https://chathura-ekanayake.medium.com/applying-event-driven-architecture-in-digital-transformation-projects-acbcb27440af",
    "upvotes": 16,
    "author": "kiyanwang",
    "comments": 2,
    "link": "https://news.ycombinator.com/item?id=30203568"
  },
  {
    "title": "What’s So Hard About Understanding Consciousness?",
    "url": "https://nautil.us/whats-so-hard-about-understanding-consciousness-13877/",
    "upvotes": 7,
    "author": "CapitalistCartr",
    "comments": 4,
    "link": "https://news.ycombinator.com/item?id=30190875"
  },
  {
    "title": "Gameboy Emulator in ARM Assembly",
    "url": "https://github.com/cottsay/arm_asm_emu",
    "upvotes": 64,
    "author": "tosh",
    "comments": 22,
    "link": "https://news.ycombinator.com/item?id=30201370"
  },
  {
    "title": "I hacked SONOS and YouTube the same day",
    "url": "https://www.deadf00d.com/post/how-i-hacked-sonos-and-youtube-the-same-day.html",
    "upvotes": 262,
    "author": "lukastyrychtr",
    "comments": 107,
    "link": "https://news.ycombinator.com/item?id=30195931"
  },
  {
    "title": "Show HN: I made a little digital circuit simulator that operates on PNGs",
    "url": "https://github.com/lynnpepin/reso",
    "upvotes": 194,
    "author": "lynndotpy",
    "comments": 40,
    "link": "https://news.ycombinator.com/item?id=30193997"
  },
  {
    "title": "Assimilate: A Flood-It game for Mac OS 9, released in 2021",
    "url": "http://www.theztd.com/assimilate/",
    "upvotes": 100,
    "author": "namu-313",
    "comments": 22,
    "link": "https://news.ycombinator.com/item?id=30176448"
  },
  {
    "title": "Show HN: Edit videos faster by automatically removing silences",
    "url": "https://www.kapwing.com/tools/smart-cut",
    "upvotes": 133,
    "author": "shahahmed",
    "comments": 69,
    "link": "https://news.ycombinator.com/item?id=30194440"
  },
  {
    "title": "How to stop running out of ephemeral ports and love long-lived connections",
    "url": "https://blog.cloudflare.com/how-to-stop-running-out-of-ephemeral-ports-and-start-to-love-long-lived-connections/",
    "upvotes": 164,
    "author": "pimterry",
    "comments": 36,
    "link": "https://news.ycombinator.com/item?id=30181710"
  },
  {
    "title": "How we broke the supply chain",
    "url": "https://prospect.org/economy/how-we-broke-the-supply-chain-intro/",
    "upvotes": 115,
    "author": "smollett",
    "comments": 76,
    "link": "https://news.ycombinator.com/item?id=30198214"
  },
  {
    "title": "Linux bcc/BPF tcplife: TCP Lifespans",
    "url": "https://www.brendangregg.com/blog/2016-11-30/linux-bcc-tcplife.html",
    "upvotes": 58,
    "author": "jaytaylor",
    "comments": 4,
    "link": "https://news.ycombinator.com/item?id=30171712"
  },
  {
    "title": "Slackware 15.0",
    "url": "http://www.slackware.com/releasenotes/15.0.php",
    "upvotes": 337,
    "author": "kdtsh",
    "comments": 144,
    "link": "https://news.ycombinator.com/item?id=30200134"
  },
  {
    "title": "A Gas Dynamics Toolkit in D",
    "url": "https://dlang.org/blog/2022/02/02/a-gas-dynamics-toolkit-in-d/",
    "upvotes": 47,
    "author": "pjmlp",
    "comments": 2,
    "link": "https://news.ycombinator.com/item?id=30176778"
  },
  {
    "title": "Launch HN: Ploomber",
    "url": "https://github.com/ploomber/ploomber",
    "upvotes": 114,
    "author": "edublancas",
    "comments": 18,
    "link": "https://news.ycombinator.com/item?id=30195191"
  },
  {
    "title": "Everyday objects can run artificial intelligence programs",
    "url": "https://www.science.org/content/article/everyday-objects-can-run-artificial-intelligence-programs",
    "upvotes": 15,
    "author": "stichers",
    "comments": 2,
    "link": "https://news.ycombinator.com/item?id=30175581"
  },
  {
    "title": "Silenced AirTags with disabled speakers are popping up for sale online",
    "url": "https://gizmodo.com/silenced-airtags-with-disabled-speakers-for-sale-online-1848473673",
    "upvotes": 283,
    "author": "gumby",
    "comments": 336,
    "link": "https://news.ycombinator.com/item?id=30196371"
  },
  {
    "title": "An 8-year-old slid his handwritten book onto a library shelf",
    "url": "https://www.washingtonpost.com/lifestyle/2022/01/31/library-book-idaho-dillon-helbig/",
    "upvotes": 312,
    "author": "TruffleLabs",
    "comments": 73,
    "link": "https://news.ycombinator.com/item?id=30173965"
  },
  {
    "title": "Why Not ZFS",
    "url": "https://storytime.ivysaur.me/posts/why-not-zfs/",
    "upvotes": 95,
    "author": "zdw",
    "comments": 129,
    "link": "https://news.ycombinator.com/item?id=30200339"
  },
  {
    "title": "Facebook loses users for the first time",
    "url": "https://www.washingtonpost.com/technology/2022/02/02/facebook-earnings-meta/",
    "upvotes": 1655,
    "author": "prostoalex",
    "comments": 1273,
    "link": "https://news.ycombinator.com/item?id=30186326"
  },
  {
    "title": "Openbase",
    "url": "https://www.ycombinator.com/companies/openbase/jobs/G21nU8U-community-manager"
  },
  {
    "title": "Compensation Data and Trends in the USA",
    "url": "https://dataforest.sequoia.com/reports/compensation/",
    "upvotes": 143,
    "author": "mattgreg",
    "comments": 84,
    "link": "https://news.ycombinator.com/item?id=30200644"
  }
]
