[
  {
    "title": "The best engineering interview question I've ever gotten",
    "url": "https://quuxplusone.github.io/blog/2022/01/06/memcached-interview/",
    "upvotes": 486,
    "author": "db48x",
    "comments": 249,
    "link": "https://news.ycombinator.com/item?id=31065143"
  },
  {
    "title": "Cytopia: Open-source city simulator with pixel-art graphics",
    "url": "https://github.com/CytopiaTeam/Cytopia",
    "upvotes": 124,
    "author": "poser-boy",
    "comments": 21,
    "link": "https://news.ycombinator.com/item?id=31066478"
  },
  {
    "title": "The casualties at the other end of the remote-controlled kill",
    "url": "https://www.nytimes.com/2022/04/15/us/drones-airstrikes-ptsd.html",
    "upvotes": 53,
    "author": "igonvalue",
    "comments": 50,
    "link": "https://news.ycombinator.com/item?id=31051334"
  },
  {
    "title": "Unreal vs. Unity Opinion",
    "url": "https://gist.github.com/flibitijibibo/035087d8736441786b10e8c3879d50dd",
    "upvotes": 264,
    "author": "ibobev",
    "comments": 142,
    "link": "https://news.ycombinator.com/item?id=31064552"
  },
  {
    "title": "Samsung Electronics cultural issues causing disasters in foundry, LSI, DRAM",
    "url": "https://semianalysis.substack.com/p/samsung-electronics-cultural-issues",
    "upvotes": 242,
    "author": "craigjb",
    "comments": 128,
    "link": "https://news.ycombinator.com/item?id=31064080"
  },
  {
    "title": "People Who Decide What Becomes History",
    "url": "https://www.newyorker.com/magazine/2022/04/18/the-people-who-decide-what-becomes-history-richard-cohen-making-history",
    "upvotes": 17,
    "author": "samclemens",
    "comments": 12,
    "link": "https://news.ycombinator.com/item?id=31049847"
  },
  {
    "title": "‘Click to Cancel’ legislation introduced in Pennsylvania",
    "url": "https://pahouse.com/InTheNews/NewsRelease/?id=124404",
    "upvotes": 272,
    "author": "barlo",
    "comments": 154,
    "link": "https://news.ycombinator.com/item?id=31066553"
  },
  {
    "title": "Richard Stallman – The state of the Free Software movement",
    "url": "https://lunduke.substack.com/p/richard-stallman-the-state-of-the",
    "upvotes": 249,
    "author": "WoodenChair",
    "comments": 279,
    "link": "https://news.ycombinator.com/item?id=31065575"
  },
  {
    "title": "The Musl Preprocessor Debate",
    "url": "https://catfox.life/2022/04/16/the-musl-preprocessor-debate/",
    "upvotes": 30,
    "author": "pabs3",
    "comments": 10,
    "link": "https://news.ycombinator.com/item?id=31067059"
  },
  {
    "title": "Assume your devices are compromised",
    "url": "https://www.go350.com/posts/digital-secrets/",
    "upvotes": 224,
    "author": "_wldu",
    "comments": 121,
    "link": "https://news.ycombinator.com/item?id=31063702"
  },
  {
    "title": "Ancient tombs and statues unearthed beneath Notre Dame Cathedral",
    "url": "https://www.theguardian.com/world/2022/apr/14/ancient-tombs-statues-notre-dame-cathedral-archaeological-dig",
    "upvotes": 84,
    "author": "apollinaire",
    "comments": 15,
    "link": "https://news.ycombinator.com/item?id=31034543"
  },
  {
    "title": "Off Belief Learning",
    "url": "https://ai.facebook.com/blog/teaching-ai-to-be-more-collaborative-with-humans-without-learning-directly-from-them/",
    "upvotes": 18,
    "author": "yamrzou",
    "comments": null,
    "link": "https://news.ycombinator.com/item?id=31051391"
  },
  {
    "title": "The games Nintendo didn't want you to play: Tengen",
    "url": "https://nicole.express/2022/the-center-point-can-not-hold.html",
    "upvotes": 298,
    "author": "luu",
    "comments": 83,
    "link": "https://news.ycombinator.com/item?id=31061154"
  },
  {
    "title": "Types of Deceptive Design",
    "url": "https://www.deceptive.design/types",
    "upvotes": 44,
    "author": "behnamoh",
    "comments": 9,
    "link": "https://news.ycombinator.com/item?id=31066658"
  },
  {
    "title": "Show HN: Giggle – A self-hosted customizable and ad-free Google Search interface",
    "url": "https://github.com/dan-lovelace/giggle",
    "upvotes": 18,
    "author": "dandrew5",
    "comments": 9,
    "link": "https://news.ycombinator.com/item?id=31067354"
  },
  {
    "title": "Ask HN: Internet magically gets faster when opening speedtest?",
    "url": "item?id=31062799",
    "upvotes": 479,
    "author": "halgir",
    "comments": 296,
    "link": "https://news.ycombinator.com/item?id=31062799"
  },
  {
    "title": "Run end-to-end tests faster with Firecracker",
    "url": "https://webapp.io/blog/github-actions-10x-faster-with-firecracker/",
    "upvotes": 170,
    "author": "samanthachai",
    "comments": 52,
    "link": "https://news.ycombinator.com/item?id=31062301"
  },
  {
    "title": "Archaeologists unearth ancient Sumerian riverboat in Iraq",
    "url": "https://arstechnica.com/science/2022/04/archaeologists-unearth-ancient-sumerian-riverboat-in-iraq/",
    "upvotes": 67,
    "author": "diodorus",
    "comments": 9,
    "link": "https://news.ycombinator.com/item?id=31033936"
  },
  {
    "title": "Dexed FM synthesizer similar to DX7 running on bare metal Raspberry Pi",
    "url": "https://github.com/probonopd/MiniDexed",
    "upvotes": 146,
    "author": "rcarmo",
    "comments": 27,
    "link": "https://news.ycombinator.com/item?id=31062237"
  },
  {
    "title": "The Trouble with Five",
    "url": "https://plus.maths.org/content/trouble-five",
    "upvotes": 29,
    "author": "the-mitr",
    "comments": 4,
    "link": "https://news.ycombinator.com/item?id=31051488"
  },
  {
    "title": "The New Old Way of Learning Languages",
    "url": "https://theamericanscholar.org/the-new-old-way-of-learning-languages/",
    "upvotes": 63,
    "author": "Tomte",
    "comments": 19,
    "link": "https://news.ycombinator.com/item?id=31064421"
  },
  {
    "title": "Show HN: \"q\", a DNS query tool with support for UDP, TCP, DoT, DoH, DoQ and ODoH",
    "url": "https://github.com/natesales/q",
    "upvotes": 76,
    "author": "natesales",
    "comments": 23,
    "link": "https://news.ycombinator.com/item?id=31064423"
  },
  {
    "title": "Tools we use to make our game satisfactory [video]",
    "url": "https://www.youtube.com/watch?v=o6ao9-UIZIQ",
    "upvotes": 78,
    "author": "mbrodersen",
    "comments": 15,
    "link": "https://news.ycombinator.com/item?id=31037430"
  },
  {
    "title": "With every good film I see, I feel reborn",
    "url": "https://www.sabzian.be/article/hossein-sabzian",
    "upvotes": 87,
    "author": "pizza",
    "comments": 28,
    "link": "https://news.ycombinator.com/item?id=31063343"
  },
  {
    "title": "How to write more clearly, think more clearly, and learn complex material [pdf]",
    "url": "http://www.covingtoninnovations.com/mc/WriteThinkLearn.pdf",
    "upvotes": 605,
    "author": "Secrethus",
    "comments": 108,
    "link": "https://news.ycombinator.com/item?id=31060362"
  },
  {
    "title": "BuildZoom",
    "url": "https://jobs.lever.co/buildzoom"
  },
  {
    "title": "“YouTube-dl” and “Pirate Bay” back on DDG",
    "url": "https://fosstodon.org/@rudolf/108147439615842718",
    "upvotes": 407,
    "author": "ikt",
    "comments": 173,
    "link": "https://news.ycombinator.com/item?id=31061163"
  },
  {
    "title": "Should we be eating three meals a day?",
    "url": "https://www.bbc.com/future/article/20220412-should-we-be-eating-three-meals-a-day",
    "upvotes": 11,
    "author": "Kaibeezy",
    "comments": 3,
    "link": "https://news.ycombinator.com/item?id=31068170"
  },
  {
    "title": "Warpgate: Smart SSH bastion that works with any SSH client",
    "url": "https://github.com/warp-tech/warpgate",
    "upvotes": 92,
    "author": "todsacerdoti",
    "comments": 17,
    "link": "https://news.ycombinator.com/item?id=31062399"
  },
  {
    "title": "Clojure Dart",
    "url": "https://github.com/Tensegritics/ClojureDart/blob/main/doc/quick-start.md",
    "upvotes": 143,
    "author": "coltnz",
    "comments": 35,
    "link": "https://news.ycombinator.com/item?id=31050693"
  }
]
