[
  {
    "title": "Shenanigans on Microsoft Feedback Hub",
    "url": "https://thomask.sdf.org/blog/2022/01/16/shenanigans-on-microsoft-feedback-hub.html",
    "upvotes": 183,
    "author": "Aaronn",
    "comments": 75,
    "link": "https://news.ycombinator.com/item?id=29954266"
  },
  {
    "title": "Why Galesburg has no money",
    "url": "https://inlandnobody.substack.com/p/why-galesburg-has-no-money",
    "upvotes": 82,
    "author": "ingve",
    "comments": 59,
    "link": "https://news.ycombinator.com/item?id=29954607"
  },
  {
    "title": "You shouldn't have your crypto designed by a CEO",
    "url": "https://mailarchive.ietf.org/arch/msg/cose/8ywbcUy-YQZUh0JF4W5Tto1dCvg/",
    "upvotes": 50,
    "author": "rdpintqogeogsaa",
    "comments": 9,
    "link": "https://news.ycombinator.com/item?id=29954822"
  },
  {
    "title": "Essence: Desktop operating system built from scratch",
    "url": "https://nakst.gitlab.io/essence",
    "upvotes": 784,
    "author": "nbaksalyar",
    "comments": 177,
    "link": "https://news.ycombinator.com/item?id=29950740"
  },
  {
    "title": "Sci Hub Injector",
    "url": "https://github.com/rickwierenga/sci-hub-injector",
    "upvotes": 112,
    "author": "sixtyfourbits",
    "comments": 21,
    "link": "https://news.ycombinator.com/item?id=29954046"
  },
  {
    "title": "Cheezam – Shazam for Cheese",
    "url": "https://cheezam.fr/",
    "upvotes": 8,
    "author": "svenfaw",
    "comments": 3,
    "link": "https://news.ycombinator.com/item?id=29955475"
  },
  {
    "title": "Do Success Stories Cause False Beliefs About Success?",
    "url": "https://www.asc.upenn.edu/news-events/news/do-success-stories-cause-false-beliefs-about-success",
    "upvotes": 102,
    "author": "rustoo",
    "comments": 117,
    "link": "https://news.ycombinator.com/item?id=29954118"
  },
  {
    "title": "Sirum is hiring developers to help uninsured people afford medicine",
    "url": "item?id=29955269"
  },
  {
    "title": "The Heaven’s Gate website is still live 25 years after all the members perished",
    "url": "https://thebodyintl.com/cults/left-alive-and-unchanged-the-heavens-gate-website",
    "upvotes": 101,
    "author": "syranwarner",
    "comments": 60,
    "link": "https://news.ycombinator.com/item?id=29954025"
  },
  {
    "title": "Kosovo pulls plug on energy-guzzling Bitcoin miners",
    "url": "https://www.theguardian.com/technology/2022/jan/16/panic-as-kosovo-pulls-the-plug-on-its-energy-guzzling-bitcoin-miners",
    "upvotes": 86,
    "author": "mafro",
    "comments": 65,
    "link": "https://news.ycombinator.com/item?id=29954910"
  },
  {
    "title": "How Tumblr Became Popular for Being Obsolete",
    "url": "https://www.newyorker.com/culture/infinite-scroll/how-tumblr-became-popular-for-being-obsolete",
    "upvotes": 22,
    "author": "ingve",
    "comments": 11,
    "link": "https://news.ycombinator.com/item?id=29954754"
  },
  {
    "title": "United Nuclear Spinthariscopes",
    "url": "https://unitednuclear.com/index.php?main_page=index&cPath=2_12",
    "upvotes": 28,
    "author": "yesenadam",
    "comments": 3,
    "link": "https://news.ycombinator.com/item?id=29943965"
  },
  {
    "title": "Quadrable: Multiversion DB – Sparse binary Merkle tree with partial-tree proofs",
    "url": "https://github.com/hoytech/quadrable",
    "upvotes": 43,
    "author": "passing",
    "comments": 3,
    "link": "https://news.ycombinator.com/item?id=29948033"
  },
  {
    "title": "The Medieval Queens Whose Daring, Murderous Reigns Were Quickly Forgotten",
    "url": "https://www.smithsonianmag.com/history/medieval-queens-daring-reigns-quickly-forgotten-180979246/",
    "upvotes": 12,
    "author": "bryanrasmussen",
    "comments": null,
    "link": "https://news.ycombinator.com/item?id=29944230"
  },
  {
    "title": "No Way to Be Human: We now occupy a nearly natureless world",
    "url": "https://www.theatlantic.com/technology/archive/2022/01/machine-garden-natureless-world/621268/",
    "upvotes": 18,
    "author": "bryanrasmussen",
    "comments": 8,
    "link": "https://news.ycombinator.com/item?id=29955222"
  },
  {
    "title": "BBC licence fee to be abolished in 2027 and funding frozen",
    "url": "https://www.theguardian.com/media/2022/jan/16/bbc-licence-fee-to-be-abolished-in-2027-and-funding-frozen",
    "upvotes": 56,
    "author": "pseudolus",
    "comments": 62,
    "link": "https://news.ycombinator.com/item?id=29955142"
  },
  {
    "title": "Lisp Badge",
    "url": "http://www.technoblogy.com/show?2AEE",
    "upvotes": 77,
    "author": "tosh",
    "comments": 11,
    "link": "https://news.ycombinator.com/item?id=29945235"
  },
  {
    "title": "Welcome to the land that no country wants: Bir Tawil",
    "url": "https://www.theguardian.com/world/2016/mar/03/welcome-to-the-land-that-no-country-wants-bir-tawil",
    "upvotes": 121,
    "author": "Thevet",
    "comments": 64,
    "link": "https://news.ycombinator.com/item?id=29943383"
  },
  {
    "title": "Letting Go of Random",
    "url": "https://www.bit-101.com/blog/2022/01/letting-go-of-random/",
    "upvotes": 27,
    "author": "ingve",
    "comments": 2,
    "link": "https://news.ycombinator.com/item?id=29945368"
  },
  {
    "title": "Saffron, the most expensive spice",
    "url": "https://gastropod.com/meet-saffron-the-worlds-most-expensive-spice/",
    "upvotes": 27,
    "author": "baxtr",
    "comments": 7,
    "link": "https://news.ycombinator.com/item?id=29949923"
  },
  {
    "title": "The Gates of Hell",
    "url": "https://www.atlasobscura.com/places/the-gates-of-hell-turkmenistan",
    "upvotes": 119,
    "author": "joak",
    "comments": 62,
    "link": "https://news.ycombinator.com/item?id=29950874"
  },
  {
    "title": "Rewatch: Stargate SG-1",
    "url": "https://macmanx.com/2019/07/22/rewatch-stargate-sg-1/",
    "upvotes": 74,
    "author": "walterbell",
    "comments": 73,
    "link": "https://news.ycombinator.com/item?id=29953579"
  },
  {
    "title": "Carbon dating is getting a major reboot",
    "url": "https://www.nature.com/articles/d41586-020-01499-y",
    "upvotes": 36,
    "author": "rammy1234",
    "comments": 13,
    "link": "https://news.ycombinator.com/item?id=29952909"
  },
  {
    "title": "HTML is/as a programming language",
    "url": "https://github.com/marianoguerra/hiapl",
    "upvotes": 83,
    "author": "marianoguerra",
    "comments": 42,
    "link": "https://news.ycombinator.com/item?id=29933608"
  },
  {
    "title": "Jane Jacobs' Legacy",
    "url": "http://www.peterdreier.com/wp-content/uploads/2014/04/Jane_Jacobs_Legacy.pdf",
    "upvotes": 18,
    "author": "Tomte",
    "comments": 2,
    "link": "https://news.ycombinator.com/item?id=29947020"
  },
  {
    "title": "Show HN: Brew.fm – An alliance of artists who remix and edit each other's tracks",
    "url": "https://www.brew.fm/",
    "upvotes": 53,
    "author": "bartproost",
    "comments": 6,
    "link": "https://news.ycombinator.com/item?id=29952633"
  },
  {
    "title": "Why Foreign Function Interfaces are not an easy answer",
    "url": "https://flameeyes.blog/2012/03/07/why-foreign-function-interfaces-are-not-an-easy-answer/",
    "upvotes": 7,
    "author": "wheresvic4",
    "comments": 2,
    "link": "https://news.ycombinator.com/item?id=29954222"
  },
  {
    "title": "Are warp drives science now?",
    "url": "http://backreaction.blogspot.com/2022/01/are-warp-drives-science-now.html",
    "upvotes": 105,
    "author": "nsoonhui",
    "comments": 41,
    "link": "https://news.ycombinator.com/item?id=29952591"
  },
  {
    "title": "Writing a minimal Lua implementation with a virtual machine from scratch in Rust",
    "url": "https://notes.eatonphil.com/lua-in-rust.html",
    "upvotes": 115,
    "author": "finite_jest",
    "comments": 19,
    "link": "https://news.ycombinator.com/item?id=29952516"
  },
  {
    "title": "Large Eruption Near Tonga, Heard in NZ. Tsunami at Tonga and Fiji",
    "url": "https://earthquake.usgs.gov/earthquakes/eventpage/pt22015050/executive",
    "upvotes": 826,
    "author": "ggm",
    "comments": 195,
    "link": "https://news.ycombinator.com/item?id=29944527"
  }
]
