[
  {
    "title": "Disclosure of three 0-day iOS vulnerabilities",
    "url": "https://habr.com/en/post/579714/",
    "upvotes": 448,
    "author": "jayhoon",
    "comments": 92,
    "link": "https://news.ycombinator.com/item?id=28637276"
  },
  {
    "title": "Apple's Power Move to Kneecap Facebook Advertising Is Working",
    "url": "https://bigtechnology.substack.com/p/completely-running-blind-apples-power",
    "upvotes": 142,
    "author": "exolymph",
    "comments": 80,
    "link": "https://news.ycombinator.com/item?id=28637062"
  },
  {
    "title": "Slacktyping: I'm typing when you're typing",
    "url": "https://github.com/will/slacktyping",
    "upvotes": 363,
    "author": "thunderbong",
    "comments": 96,
    "link": "https://news.ycombinator.com/item?id=28634831"
  },
  {
    "title": "It's tough being an Azure fan",
    "url": "https://www.alexhudson.com/2021/09/17/its-tough-being-an-azure-fan/",
    "upvotes": 222,
    "author": "ealexhudson",
    "comments": 150,
    "link": "https://news.ycombinator.com/item?id=28617663"
  },
  {
    "title": "AI powered LEDs for veins finding",
    "url": "https://christiemed.com/vein-illumination/",
    "upvotes": 9,
    "author": "piniiforever",
    "comments": null,
    "link": "https://news.ycombinator.com/item?id=28638578"
  },
  {
    "title": "Know Labs unveils glucose monitor that swaps fingersticks for RF sensors",
    "url": "https://www.fiercebiotech.com/medtech/know-labs-unveils-pocket-sized-glucose-monitor-swaps-fingersticks-for-radiofrequency",
    "upvotes": 72,
    "author": "coatta",
    "comments": 46,
    "link": "https://news.ycombinator.com/item?id=28636926"
  },
  {
    "title": "Elk: A low footprint JavaScript engine for embedded systems",
    "url": "https://github.com/cesanta/elk",
    "upvotes": 80,
    "author": "pjf",
    "comments": 29,
    "link": "https://news.ycombinator.com/item?id=28614092"
  },
  {
    "title": "Reactive Clojure: A web language",
    "url": "https://hyperfiddle.notion.site/hyperfiddle/Reactive-Clojure-You-don-t-need-a-web-framework-you-need-a-web-language-44b5bfa526be4af282863f34fa1cfffc",
    "upvotes": 398,
    "author": "audionerd",
    "comments": 152,
    "link": "https://news.ycombinator.com/item?id=28630209"
  },
  {
    "title": "Using two keyboards at once for pain relief",
    "url": "https://symboliclogic.io/years-of-pain-solved-by-really-obvious-keyboard-tweak/",
    "upvotes": 278,
    "author": "ruffrey",
    "comments": 243,
    "link": "https://news.ycombinator.com/item?id=28631435"
  },
  {
    "title": "Fourier Series Visualisation with D3",
    "url": "https://bl.ocks.org/jinroh/7524988",
    "upvotes": 200,
    "author": "colinprince",
    "comments": 38,
    "link": "https://news.ycombinator.com/item?id=28632776"
  },
  {
    "title": "Embedded social media posts might now be illegal",
    "url": "https://maya.land/monologues/2021/09/21/illegal-fox-picture.html",
    "upvotes": 24,
    "author": "kixiQu",
    "comments": 3,
    "link": "https://news.ycombinator.com/item?id=28619684"
  },
  {
    "title": "Quitting your dream job twice",
    "url": "https://t3.gg/blog/posts/quitting",
    "upvotes": 56,
    "author": "purgator",
    "comments": 12,
    "link": "https://news.ycombinator.com/item?id=28622669"
  },
  {
    "title": "Book review: The Checklist Manifesto",
    "url": "https://www.lesswrong.com/posts/dtmmP4YdJEfK9y4Rc/book-review-the-checklist-manifesto",
    "upvotes": 124,
    "author": "lobbly",
    "comments": 65,
    "link": "https://news.ycombinator.com/item?id=28622867"
  },
  {
    "title": "Show HN: Go playground powered by WASM that runs in the browser",
    "url": "https://go-playground-wasm.vercel.app/",
    "upvotes": 59,
    "author": "zackoverflow",
    "comments": 19,
    "link": "https://news.ycombinator.com/item?id=28636540"
  },
  {
    "title": "San Francisco’s bizarre, costly quest for the perfect trash can",
    "url": "https://missionlocal.org/2021/09/san-francisco-garbage-can-designer/",
    "upvotes": 23,
    "author": "savanaly",
    "comments": 8,
    "link": "https://news.ycombinator.com/item?id=28638494"
  },
  {
    "title": "Facebook paid billions to spare Zuckerberg in data suit, shareholders allege",
    "url": "https://www.politico.com/news/2021/09/21/facebook-paid-billions-extra-to-the-ftc-to-spare-zuckerberg-in-data-suit-shareholders-allege-513456",
    "upvotes": 503,
    "author": "croes",
    "comments": 291,
    "link": "https://news.ycombinator.com/item?id=28632565"
  },
  {
    "title": "Catala Lang: DSL designed for deriving implementations from legislative texts",
    "url": "https://catala-lang.org/",
    "upvotes": 76,
    "author": "wut42",
    "comments": 28,
    "link": "https://news.ycombinator.com/item?id=28633122"
  },
  {
    "title": "Discontinue Sourcetrail",
    "url": "https://sourcetrail.com/blog/discontinue_sourcetrail/",
    "upvotes": 28,
    "author": "pabs3",
    "comments": 10,
    "link": "https://news.ycombinator.com/item?id=28637193"
  },
  {
    "title": "Dog parasite is developing resistance to treatments",
    "url": "https://news.uga.edu/hookworms-are-developing-resistance-to-medications/",
    "upvotes": 136,
    "author": "gmays",
    "comments": 74,
    "link": "https://news.ycombinator.com/item?id=28631309"
  },
  {
    "title": "Avoiding the audience paradox when writing job descriptions",
    "url": "https://blog.interviewing.io/how-to-write-good-job-descriptions/",
    "upvotes": 30,
    "author": "leeny",
    "comments": 24,
    "link": "https://news.ycombinator.com/item?id=28630431"
  },
  {
    "title": "BuildZoom",
    "url": "https://jobs.lever.co/buildzoom"
  },
  {
    "title": "A Tour of Grant Imahara’s Shop [video]",
    "url": "https://www.youtube.com/watch?v=hsCSTO8SaQU",
    "upvotes": 109,
    "author": "vo2maxer",
    "comments": 44,
    "link": "https://news.ycombinator.com/item?id=28633605"
  },
  {
    "title": "How Fast Do Algorithms Improve? [pdf]",
    "url": "https://ieeexplore.ieee.org/stamp/stamp.jsp?tp=&arnumber=9540991",
    "upvotes": 44,
    "author": "djoldman",
    "comments": 5,
    "link": "https://news.ycombinator.com/item?id=28621057"
  },
  {
    "title": "The NSA and CIA use ad blockers",
    "url": "https://www.vice.com/en/article/93ypke/the-nsa-and-cia-use-ad-blockers-because-online-advertising-is-so-dangerous",
    "upvotes": 491,
    "author": "infodocket",
    "comments": 303,
    "link": "https://news.ycombinator.com/item?id=28631005"
  },
  {
    "title": "Show HN: Composing Studio – An online, collaborative editor for music notation",
    "url": "https://github.com/ekzhang/composing.studio",
    "upvotes": 96,
    "author": "ekzhang",
    "comments": 8,
    "link": "https://news.ycombinator.com/item?id=28615418"
  },
  {
    "title": "Google keeps records of everything you buy, even if you delete the email receipt",
    "url": "https://mastodon.social/@gerowen/106978308085702358",
    "upvotes": 672,
    "author": "decrypt",
    "comments": 330,
    "link": "https://news.ycombinator.com/item?id=28631540"
  },
  {
    "title": "Cow Dung Capitalism",
    "url": "https://openthemagazine.com/cover-stories/cow-dung-capitalism-milking-the-holy-cow/",
    "upvotes": 26,
    "author": "ordiblah",
    "comments": 11,
    "link": "https://news.ycombinator.com/item?id=28619418"
  },
  {
    "title": "Mozilla says Chrome’s latest feature enables surveillance",
    "url": "https://www.howtogeek.com/756338/mozilla-says-chromes-latest-feature-enables-surveillance/",
    "upvotes": 252,
    "author": "good8675309",
    "comments": 96,
    "link": "https://news.ycombinator.com/item?id=28632932"
  },
  {
    "title": "“Why should I use Nyxt if I can use Vimium?”",
    "url": "https://nyxt.atlas.engineer/article/nyxt-versus-plugins.org",
    "upvotes": 61,
    "author": "todsacerdoti",
    "comments": 7,
    "link": "https://news.ycombinator.com/item?id=28632422"
  },
  {
    "title": "My drowning and other inconveniences",
    "url": "https://www.outsideonline.com/outdoor-adventure/exploration-survival/my-drowning-and-other-inconveniences-2/",
    "upvotes": 32,
    "author": "allthebest",
    "comments": 6,
    "link": "https://news.ycombinator.com/item?id=28619428"
  }
]
