[
  {
    "title": "E-Ink Magic Calendar that runs off a battery powered Raspberry Pi",
    "url": "https://github.com/speedyg0nz/MagInkCal",
    "upvotes": 187,
    "author": "edward",
    "comments": 62,
    "link": "https://news.ycombinator.com/item?id=28740452"
  },
  {
    "title": "FoundationDB: A Distributed Unbundled Transactional Key Value Store",
    "url": "https://www.micahlerner.com/2021/06/12/foundationdb-a-distributed-unbundled-transactional-key-value-store.html",
    "upvotes": 67,
    "author": "mlerner",
    "comments": 10,
    "link": "https://news.ycombinator.com/item?id=28740497"
  },
  {
    "title": "Word-Aligned Bloom Filters",
    "url": "https://lemire.me/blog/2021/10/03/word-aligned-bloom-filters/",
    "upvotes": 205,
    "author": "zdw",
    "comments": 54,
    "link": "https://news.ycombinator.com/item?id=28737910"
  },
  {
    "title": "New study reveals iPhones aren't as private as you think",
    "url": "https://www.tomsguide.com/news/android-ios-data-collection",
    "upvotes": 84,
    "author": "ColinWright",
    "comments": 53,
    "link": "https://news.ycombinator.com/item?id=28741262"
  },
  {
    "title": "Unified Shader Programming in C++",
    "url": "https://arxiv.org/abs/2109.14682",
    "upvotes": 72,
    "author": "matt_d",
    "comments": 36,
    "link": "https://news.ycombinator.com/item?id=28738750"
  },
  {
    "title": "A Macintosh History 85.10",
    "url": "https://systemtalk.org/post/macintosh-history-8510/",
    "upvotes": 55,
    "author": "ingve",
    "comments": 13,
    "link": "https://news.ycombinator.com/item?id=28739998"
  },
  {
    "title": "Show HN: SpotML – Managed ML Training on Cheap AWS/GCP Spot Instances",
    "url": "https://spotml.io/",
    "upvotes": 118,
    "author": "vishnukool",
    "comments": 55,
    "link": "https://news.ycombinator.com/item?id=28738141"
  },
  {
    "title": "The FB Whistleblower, Frances Haugen, Says She Wants to Fix Company, Not Harm It",
    "url": "https://www.wsj.com/articles/facebook-whistleblower-frances-haugen-says-she-wants-to-fix-the-company-not-harm-it-11633304122",
    "upvotes": 29,
    "author": "mudil",
    "comments": 10,
    "link": "https://news.ycombinator.com/item?id=28741532"
  },
  {
    "title": "How does the economy work? A new Fed paper suggests nobody really knows",
    "url": "https://www.nytimes.com/2021/10/01/upshot/inflation-economy-analysis.html",
    "upvotes": 247,
    "author": "pseudolus",
    "comments": 248,
    "link": "https://news.ycombinator.com/item?id=28736145"
  },
  {
    "title": "DARPA's hypersonic scramjet achieves successful flight",
    "url": "https://www.darpa.mil/news-events/2021-09-27",
    "upvotes": 125,
    "author": "geox",
    "comments": 159,
    "link": "https://news.ycombinator.com/item?id=28737766"
  },
  {
    "title": "A Fire Upon the Deep by Vernor Vinge",
    "url": "https://archive.org/details/fireupondeep00ving",
    "upvotes": 246,
    "author": "cybernautique",
    "comments": 120,
    "link": "https://news.ycombinator.com/item?id=28736081"
  },
  {
    "title": "Mt32-pi: A baremetal Roland MT-32 emulator",
    "url": "https://github.com/dwhinham/mt32-pi",
    "upvotes": 83,
    "author": "rcarmo",
    "comments": 12,
    "link": "https://news.ycombinator.com/item?id=28727084"
  },
  {
    "title": "Sirum (YC Nonprofit) Is Hiring Mission-Driven Founding Engineers",
    "url": "item?id=28740459"
  },
  {
    "title": "How much information can a small image contain?",
    "url": "https://www.camerongordon.site/post/how-much-information-can-a-small-image-contain",
    "upvotes": 10,
    "author": "iciac",
    "comments": 4,
    "link": "https://news.ycombinator.com/item?id=28716233"
  },
  {
    "title": "Removing my site from Google search",
    "url": "https://www.btao.org/2021/10/03/removing-from-google/",
    "upvotes": 160,
    "author": "todsacerdoti",
    "comments": 71,
    "link": "https://news.ycombinator.com/item?id=28739081"
  },
  {
    "title": "Riesz Proves the Riesz Representation Theorem",
    "url": "http://nonagon.org/ExLibris/riesz-proves-riesz-representation-theorem",
    "upvotes": 50,
    "author": "todsacerdoti",
    "comments": 12,
    "link": "https://news.ycombinator.com/item?id=28727732"
  },
  {
    "title": "Show HN: A curated list of PaaS and tools to emulate PaaS on cloud",
    "url": "https://github.com/debarshibasak/awesome-paas",
    "upvotes": 8,
    "author": "debarshri",
    "comments": 2,
    "link": "https://news.ycombinator.com/item?id=28741125"
  },
  {
    "title": "Dune: A Shell by the Beach",
    "url": "https://github.com/adam-mcdaniel/dune",
    "upvotes": 135,
    "author": "asicsp",
    "comments": 24,
    "link": "https://news.ycombinator.com/item?id=28727566"
  },
  {
    "title": "Pandora papers: biggest leak of offshore data exposes financial secrets of rich",
    "url": "https://www.theguardian.com/news/2021/oct/03/pandora-papers-biggest-ever-leak-of-offshore-data-exposes-financial-secrets-of-rich-and-powerful",
    "upvotes": 835,
    "author": "pseudolus",
    "comments": 418,
    "link": "https://news.ycombinator.com/item?id=28738407"
  },
  {
    "title": "Data-Driven Routers",
    "url": "https://cljdoc.org/d/metosin/reitit/0.5.15/doc/introduction",
    "upvotes": 6,
    "author": "viebel",
    "comments": null,
    "link": "https://news.ycombinator.com/item?id=28715381"
  },
  {
    "title": "Mysterious Stone Orbs Stashed All over Neolithic Britain",
    "url": "https://www.atlasobscura.com/articles/mysterious-neolithic-stone-balls",
    "upvotes": 70,
    "author": "samizdis",
    "comments": 44,
    "link": "https://news.ycombinator.com/item?id=28727725"
  },
  {
    "title": "Show HN: Futurecoder – A free online interactive Python course",
    "url": "https://futurecoder.io/",
    "upvotes": 72,
    "author": "alexmojaki",
    "comments": 14,
    "link": "https://news.ycombinator.com/item?id=28737779"
  },
  {
    "title": "BANCStar: Financial Programming Language",
    "url": "https://esolangs.org/wiki/BANCStar",
    "upvotes": 29,
    "author": "merlinscholz",
    "comments": 9,
    "link": "https://news.ycombinator.com/item?id=28739144"
  },
  {
    "title": "A massive oil spill in the Pacific Ocean reached the Southern California coast",
    "url": "https://www.npr.org/2021/10/03/1042846846/a-massive-oil-spill-in-the-pacific-ocean-has-reached-the-southern-california-coa",
    "upvotes": 167,
    "author": "amelius",
    "comments": 25,
    "link": "https://news.ycombinator.com/item?id=28739577"
  },
  {
    "title": "Robotic Process Automation and Artificial Intelligence in Industry 4.0",
    "url": "https://www.sciencedirect.com/science/article/pii/S1877050921001393",
    "upvotes": 44,
    "author": "TiagoEckhardt",
    "comments": 20,
    "link": "https://news.ycombinator.com/item?id=28738024"
  },
  {
    "title": "Double-Odd Elliptic Curves",
    "url": "https://doubleodd.group/front.html",
    "upvotes": 52,
    "author": "rdpintqogeogsaa",
    "comments": 5,
    "link": "https://news.ycombinator.com/item?id=28736958"
  },
  {
    "title": "Paradoxical Compression with VDF",
    "url": "https://github.com/pornin/paradox-compress",
    "upvotes": 82,
    "author": "rdpintqogeogsaa",
    "comments": 40,
    "link": "https://news.ycombinator.com/item?id=28736949"
  },
  {
    "title": "Finally, on CBS, the football matches the business cards",
    "url": "https://www.ological.net/finally-on-cbs-the-football-matches-the-business-cards/",
    "upvotes": 117,
    "author": "starmftronajoll",
    "comments": 38,
    "link": "https://news.ycombinator.com/item?id=28738380"
  },
  {
    "title": "Supply Chain and Network Security for Military 5G Networks [pdf]",
    "url": "https://ccdcoe.org/uploads/2021/10/Report_Supply_Chain_and_Network_Security_for_Military_5G_Networks.pdf",
    "upvotes": 10,
    "author": "infodocket",
    "comments": null,
    "link": "https://news.ycombinator.com/item?id=28740406"
  },
  {
    "title": "The Nernst Lamp",
    "url": "https://edisontechcenter.org/NernstLamps.html",
    "upvotes": 21,
    "author": "rolph",
    "comments": 4,
    "link": "https://news.ycombinator.com/item?id=28739587"
  }
]
